smally.py
smally-0.525.dist-info/METADATA
smally-0.525.dist-info/WHEEL
smally-0.525.dist-info/licenses/LICENSE
smally-0.525.dist-info/RECORD
