Metadata-Version: 2.1
Name: smally
Version: 0.525
Summary: To compress JPEG, PNG and GIF files losslessly in batch mode
Project-URL: homepage, https://github.com/xinlin-z/smally
Author-email: xinlin-z <xinlin.zhang@hotmail.com>
License: MIT License
License-File: LICENSE
Keywords: GIF,JPEG,PNG,batch,compress
Classifier: License :: OSI Approved :: MIT License
Classifier: Operating System :: POSIX
Classifier: Programming Language :: Python :: 3
Requires-Python: >=3.8
